{
  "beta_10": {
    "Isotropic": {
      "mean": 159.25,
      "std": 93.46,
      "median": 141.50,
      "skew": 1.36,
      "kurtosis": 3.03,
      "IQR": 110.00,
      "p95": 335.65,
      "p99": 474.53,
      "Failure Rate (%)": 0.00
    },
    "Aniso-Small": {
      "mean": 147.90,
      "std": 87.04,
      "median": 131.00,
      "skew": 1.46,
      "kurtosis": 3.98,
      "IQR": 101.00,
      "p95": 310.65,
      "p99": 441.06,
      "Failure Rate (%)": 0.00
    },
    "Aniso-Large": {
      "mean": 1940.19,
      "std": 1952.96,
      "median": 1313.00,
      "skew": 1.94,
      "kurtosis": 5.43,
      "IQR": 2088.25,
      "p95": 5943.75,
      "p99": 8444.92,
      "Failure Rate (%)": 0.00
    }
  },
  "beta_100": {
    "Isotropic": {
      "mean": 130.03,
      "std": 81.37,
      "median": 113.50,
      "skew": 2.68,
      "kurtosis": 13.89,
      "IQR": 81.00,
      "p95": 267.00,
      "p99": 434.12,
      "Failure Rate (%)": 0.00
    },
    "Aniso-Small": {
      "mean": 126.90,
      "std": 73.74,
      "median": 111.00,
      "skew": 1.93,
      "kurtosis": 6.99,
      "IQR": 81.00,
      "p95": 255.65,
      "p99": 385.00,
      "Failure Rate (%)": 0.00
    },
    "Aniso-Large": {
      "mean": 187.99,
      "std": 117.06,
      "median": 165.50,
      "skew": 1.45,
      "kurtosis": 4.00,
      "IQR": 139.00,
      "p95": 406.65,
      "p99": 554.59,
      "Failure Rate (%)": 0.00
    }
  }
}